ez_datastructure/__init__.py
ez_datastructure/linked_list.py
ez_datastructure-0.0.1.dist-info/METADATA
ez_datastructure-0.0.1.dist-info/WHEEL
ez_datastructure-0.0.1.dist-info/top_level.txt
ez_datastructure-0.0.1.dist-info/RECORD
