Metadata-Version: 2.4
Name: ez_datastructure
Version: 0.0.1
Summary: Easy Data Structures
Author: E Z
Classifier: Programming Language :: Python :: 3
Classifier: Operating System :: OS Independent
Requires-Python: >=3.9
